Workbook

Sheet Trang Bìa
B2: HỆ SINH THÁI VETUONGLAI
B3: Dự báo Tài chính 5 năm
B5: Kỳ: 2026 (Năm 1) — 2030 (Năm 5)
B6: Đơn vị: Triệu USD trừ khi ghi khác
B7: Tháng 5/2026
B9: TUYỆT MẬT — Chỉ người nhận được phép
B11: Quy ước màu
B12: Chữ xanh dương | C12: Đầu vào cố định (thay đổi cho kịch bản)
B13: Chữ đen | C13: Tất cả công thức tính toán
B14: Chữ xanh lá | C14: Liên kết giữa các sheet
B15: Nền vàng | C15: Giả định quan trọng cần chú ý
B18: Các sheet trong workbook
B19: → Giả định
B20: → Mô hình Doanh thu
B21: → Chi phí
B22: → Lãi-Lỗ
B23: → Dòng tiền
B24: → KPI Tóm tắt
B25: → Định giá
B26: → Kịch bản

Sheet Giả định
A1: Vetuonglai Dự báo Tài chính 5 năm
A2: Year | B2: 2026 | C2: 2027 | D2: 2028 | E2: 2029 | F2: 2030
A4: MEMBER GROWTH
A5: Paid members (end of year) | B5: 12000 | C5: 55000 | D5: 220000 | E5: 620000 | F5: 1650000
A6: Free members (end of year) | B6: 108000 | C6: 495000 | D6: 1980000 | E6: 5580000 | F6: 14850000
A7: Total members | B7: =B5+B6 | C7: =C5+C6 | D7: =D5+D6 | E7: =E5+E6 | F7: =F5+F6
A8: YoY paid member growth | B8: "-" | C8: =C5/B5-1 | D8: =D5/C5-1 | E8: =E5/D5-1 | F8: =F5/E5-1
A9: Annual churn | B9: 0.18 | C9: 0.15 | D9: 0.12 | E9: 0.1 | F9: 0.09
A10: Free→paid conversion | B10: 0.05 | C10: 0.07 | D10: 0.09 | E10: 0.11 | F10: 0.12
A12: PRICING (USD)
A13: Annual Access price | B13: 99 | C13: 104 | D13: 109 | E13: 115 | F13: 121
A14: Specialist Pack price (avg) | B14: 29 | C14: 31 | D14: 32 | E14: 34 | F14: 36
A15: AI Tutor price/year | B15: 120 | C15: 126 | D15: 132 | E15: 139 | F15: 146
A16: B2B Verification API ($/verif) | B16: 0.75 | C16: 0.8 | D16: 0.85 | E16: 0.9 | F16: 0.95
A17: B2B VC Issuer License/year | B17: 12000 | C17: 12500 | D17: 13000 | E17: 13500 | F17: 14000
A19: TAKE RATES & VOLUME
A20: Pack attach rate per paid member/yr | B20: 1.2 | C20: 1.5 | D20: 1.8 | E20: 2 | F20: 2.2
A21: AI Tutor attach % paid | B21: 0.1 | C21: 0.18 | D21: 0.25 | E21: 0.32 | F21: 0.38
A22: Job marketplace GMV ($M) | B22: 2 | C22: 12 | D22: 48 | E22: 145 | F22: 360
A23: Marketplace take rate % | B23: 0.09 | C23: 0.09 | D23: 0.085 | E23: 0.08 | F23: 0.08
A24: Wallet payout volume ($M) | B24: 1 | C24: 8 | D24: 35 | E24: 105 | F24: 250
A25: Wallet payout fee % | B25: 0.02 | C25: 0.02 | D25: 0.018 | E25: 0.015 | F25: 0.012
A26: Affiliate revenue ($M) | B26: 0.05 | C26: 0.4 | D26: 1.8 | E26: 5.5 | F26: 13.5
A27: B2B API verifications (M/year) | B27: 0.5 | C27: 3 | D27: 12 | E27: 35 | F27: 80
A28: B2B VC Issuer customers | B28: 2 | C28: 12 | D28: 45 | E28: 130 | F28: 320
A30: COST RATIOS
A31: Infrastructure cost % of revenue | B31: 0.06 | C31: 0.05 | D31: 0.04 | E31: 0.035 | F31: 0.03
A32: Payment processing % of revenue | B32: 0.025 | C32: 0.025 | D32: 0.024 | E32: 0.023 | F32: 0.022
A33: KYC + verification cost % rev | B33: 0.02 | C33: 0.018 | D33: 0.015 | E33: 0.012 | F33: 0.01
A34: Other COGS % of revenue | B34: 0.175 | C34: 0.147 | D34: 0.141 | E34: 0.13 | F34: 0.128
A35: Total COGS % (sum above) | B35: =B31+B32+B33+B34 | C35: =C31+C32+C33+C34 | D35: =D31+D32+D33+D34 | E35: =E31+E32+E33+E34 | F35: =F31+F32+F33+F34
A36: S&M cost % of revenue | B36: 0.45 | C36: 0.38 | D36: 0.32 | E36: 0.28 | F36: 0.25
A37: R&D cost % of revenue | B37: 0.35 | C37: 0.28 | D37: 0.22 | E37: 0.18 | F37: 0.15
A38: G&A cost % of revenue | B38: 0.18 | C38: 0.14 | D38: 0.1 | E38: 0.08 | F38: 0.07
A40: MACRO & VALUATION
A41: Effective tax rate | B41: 0 | C41: 0 | D41: 0.1 | E41: 0.2 | F41: 0.2
A42: Discount rate (WACC) | B42: 0.18
A43: Revenue multiple (mid) | B43: 10 | C43: 9.5 | D43: 7.5 | E43: 6.3 | F43: 6.3
A44: EBITDA multiple | B44: 0 | C44: 0 | D44: 25 | E44: 18 | F44: 15

Sheet Mô hình Doanh thu
A1: Mô hình Doanh thu (Triệu USD)
A2: Lane | B2: Description | C2: 2026 | D2: 2027 | E2: 2028 | F2: 2029 | G2: 2030
A3: Annual Access subscription | B3: B2C subscription — Lifetime Unlock | C3: ='Giả định'!B5*'Giả định'!B13/1000000*0.5 | D3: ='Giả định'!C5*'Giả định'!C13/1000000*1.0 | E3: ='Giả định'!D5*'Giả định'!D13/1000000*1.0 | F3: ='Giả định'!E5*'Giả định'!E13/1000000*1.0 | G3: ='Giả định'!F5*'Giả định'!F13/1000000*1.0
A4: Specialist Packs | B4: B2C mua một lần | C4: ='Giả định'!B5*'Giả định'!B20*'Giả định'!B14/1000000 | D4: ='Giả định'!C5*'Giả định'!C20*'Giả định'!C14/1000000 | E4: ='Giả định'!D5*'Giả định'!D20*'Giả định'!D14/1000000 | F4: ='Giả định'!E5*'Giả định'!E20*'Giả định'!E14/1000000 | G4: ='Giả định'!F5*'Giả định'!F20*'Giả định'!F14/1000000
A5: Job Marketplace take-rate | B5: Phí escrow + payout | C5: ='Giả định'!B22*'Giả định'!B23 | D5: ='Giả định'!C22*'Giả định'!C23 | E5: ='Giả định'!D22*'Giả định'!D23 | F5: ='Giả định'!E22*'Giả định'!E23 | G5: ='Giả định'!F22*'Giả định'!F23
A6: Phí Payout Ví | B6: Free-tier 2% rút tiền | C6: ='Giả định'!B24*'Giả định'!B25 | D6: ='Giả định'!C24*'Giả định'!C25 | E6: ='Giả định'!D24*'Giả định'!D25 | F6: ='Giả định'!E24*'Giả định'!E25 | G6: ='Giả định'!F24*'Giả định'!F25
A7: Affiliate revenue share | B7: Hoa hồng pass-through | C7: ='Giả định'!B26 | D7: ='Giả định'!C26 | E7: ='Giả định'!D26 | F7: ='Giả định'!E26 | G7: ='Giả định'!F26
A8: B2B Identity Verification API | B8: Phí mỗi verification | C8: ='Giả định'!B27*'Giả định'!B16 | D8: ='Giả định'!C27*'Giả định'!C16 | E8: ='Giả định'!D27*'Giả định'!D16 | F8: ='Giả định'!E27*'Giả định'!E16 | G8: ='Giả định'!F27*'Giả định'!F16
A9: B2B VC Issuer Licensing | B9: License năm cho issuer | C9: ='Giả định'!B28*'Giả định'!B17/1000000 | D9: ='Giả định'!C28*'Giả định'!C17/1000000 | E9: ='Giả định'!D28*'Giả định'!D17/1000000 | F9: ='Giả định'!E28*'Giả định'!E17/1000000 | G9: ='Giả định'!F28*'Giả định'!F17/1000000
A10: AI Tutor Premium | B10: Tutor hỗ trợ Anthropic | C10: ='Giả định'!B5*'Giả định'!B21*'Giả định'!B15/1000000 | D10: ='Giả định'!C5*'Giả định'!C21*'Giả định'!C15/1000000 | E10: ='Giả định'!D5*'Giả định'!D21*'Giả định'!D15/1000000 | F10: ='Giả định'!E5*'Giả định'!E21*'Giả định'!E15/1000000 | G10: ='Giả định'!F5*'Giả định'!F21*'Giả định'!F15/1000000
A12: Tổng doanh thu | C12: =SUM(C3:C10) | D12: =SUM(D3:D10) | E12: =SUM(E3:E10) | F12: =SUM(F3:F10) | G12: =SUM(G3:G10)

Sheet Chi phí
A1: Phân tích Chi phí Vận hành
A2: Item | B2: 2026 | C2: 2027 | D2: 2028 | E2: 2029 | F2: 2030
A3: Hạ tầng (Cloudflare, KV, monitoring) | B3: ='Mô hình Doanh thu'!C12*'Giả định'!B35*('Giả định'!B31/'Giả định'!B35) | C3: ='Mô hình Doanh thu'!D12*'Giả định'!C35*('Giả định'!C31/'Giả định'!C35) | D3: ='Mô hình Doanh thu'!E12*'Giả định'!D35*('Giả định'!D31/'Giả định'!D35) | E3: ='Mô hình Doanh thu'!F12*'Giả định'!E35*('Giả định'!E31/'Giả định'!E35) | F3: ='Mô hình Doanh thu'!G12*'Giả định'!F35*('Giả định'!F31/'Giả định'!F35)
A4: Xử lý thanh toán (Stripe/PayPal) | B4: ='Mô hình Doanh thu'!C12*'Giả định'!B32 | C4: ='Mô hình Doanh thu'!D12*'Giả định'!C32 | D4: ='Mô hình Doanh thu'!E12*'Giả định'!D32 | E4: ='Mô hình Doanh thu'!F12*'Giả định'!E32 | F4: ='Mô hình Doanh thu'!G12*'Giả định'!F32
A5: KYC + xác minh danh tính | B5: ='Mô hình Doanh thu'!C12*'Giả định'!B33 | C5: ='Mô hình Doanh thu'!D12*'Giả định'!C33 | D5: ='Mô hình Doanh thu'!E12*'Giả định'!D33 | E5: ='Mô hình Doanh thu'!F12*'Giả định'!E33 | F5: ='Mô hình Doanh thu'!G12*'Giả định'!F33
A6: COGS khác (support, content, misc) | B6: ='Mô hình Doanh thu'!C12*'Giả định'!B34 | C6: ='Mô hình Doanh thu'!D12*'Giả định'!C34 | D6: ='Mô hình Doanh thu'!E12*'Giả định'!D34 | E6: ='Mô hình Doanh thu'!F12*'Giả định'!E34 | F6: ='Mô hình Doanh thu'!G12*'Giả định'!F34
A7: Tổng COGS | B7: ='Mô hình Doanh thu'!C12*'Giả định'!B35 | C7: ='Mô hình Doanh thu'!D12*'Giả định'!C35 | D7: ='Mô hình Doanh thu'!E12*'Giả định'!D35 | E7: ='Mô hình Doanh thu'!F12*'Giả định'!E35 | F7: ='Mô hình Doanh thu'!G12*'Giả định'!F35
A8: Sales & Marketing | B8: ='Mô hình Doanh thu'!C12*'Giả định'!B36 | C8: ='Mô hình Doanh thu'!D12*'Giả định'!C36 | D8: ='Mô hình Doanh thu'!E12*'Giả định'!D36 | E8: ='Mô hình Doanh thu'!F12*'Giả định'!E36 | F8: ='Mô hình Doanh thu'!G12*'Giả định'!F36
A9: R&D / Kỹ thuật | B9: ='Mô hình Doanh thu'!C12*'Giả định'!B37 | C9: ='Mô hình Doanh thu'!D12*'Giả định'!C37 | D9: ='Mô hình Doanh thu'!E12*'Giả định'!D37 | E9: ='Mô hình Doanh thu'!F12*'Giả định'!E37 | F9: ='Mô hình Doanh thu'!G12*'Giả định'!F37
A10: G&A | B10: ='Mô hình Doanh thu'!C12*'Giả định'!B38 | C10: ='Mô hình Doanh thu'!D12*'Giả định'!C38 | D10: ='Mô hình Doanh thu'!E12*'Giả định'!D38 | E10: ='Mô hình Doanh thu'!F12*'Giả định'!E38 | F10: ='Mô hình Doanh thu'!G12*'Giả định'!F38
A11: Tổng Chi phí Vận hành | B11: ='Mô hình Doanh thu'!C12*('Giả định'!B36+'Giả định'!B37+'Giả định'!B38) | C11: ='Mô hình Doanh thu'!D12*('Giả định'!C36+'Giả định'!C37+'Giả định'!C38) | D11: ='Mô hình Doanh thu'!E12*('Giả định'!D36+'Giả định'!D37+'Giả định'!D38) | E11: ='Mô hình Doanh thu'!F12*('Giả định'!E36+'Giả định'!E37+'Giả định'!E38) | F11: ='Mô hình Doanh thu'!G12*('Giả định'!F36+'Giả định'!F37+'Giả định'!F38)

Sheet Lãi-Lỗ
A1: Báo cáo Lãi Lỗ
A2: Item | B2: 2026 | C2: 2027 | D2: 2028 | E2: 2029 | F2: 2030
A3: Doanh thu | B3: ='Mô hình Doanh thu'!C12 | C3: ='Mô hình Doanh thu'!D12 | D3: ='Mô hình Doanh thu'!E12 | E3: ='Mô hình Doanh thu'!F12 | F3: ='Mô hình Doanh thu'!G12
A4: COGS (hạ tầng + thanh toán + KYC) | B4: =B3*'Giả định'!B35 | C4: =C3*'Giả định'!C35 | D4: =D3*'Giả định'!D35 | E4: =E3*'Giả định'!E35 | F4: =F3*'Giả định'!F35
A5: Lãi gộp | B5: =B3-B4 | C5: =C3-C4 | D5: =D3-D4 | E5: =E3-E4 | F5: =F3-F4
A6: Biên gộp % | B6: =IF(B3=0,0,B5/B3) | C6: =IF(C3=0,0,C5/C3) | D6: =IF(D3=0,0,D5/D3) | E6: =IF(E3=0,0,E5/E3) | F6: =IF(F3=0,0,F5/F3)
A7: Sales & Marketing | B7: =B3*'Giả định'!B36 | C7: =C3*'Giả định'!C36 | D7: =D3*'Giả định'!D36 | E7: =E3*'Giả định'!E36 | F7: =F3*'Giả định'!F36
A8: R&D / Kỹ thuật | B8: =B3*'Giả định'!B37 | C8: =C3*'Giả định'!C37 | D8: =D3*'Giả định'!D37 | E8: =E3*'Giả định'!E37 | F8: =F3*'Giả định'!F37
A9: G&A | B9: =B3*'Giả định'!B38 | C9: =C3*'Giả định'!C38 | D9: =D3*'Giả định'!D38 | E9: =E3*'Giả định'!E38 | F9: =F3*'Giả định'!F38
A10: Tổng Opex | B10: =B7+B8+B9 | C10: =C7+C8+C9 | D10: =D7+D8+D9 | E10: =E7+E8+E9 | F10: =F7+F8+F9
A11: EBITDA | B11: =B5-B10 | C11: =C5-C10 | D11: =D5-D10 | E11: =E5-E10 | F11: =F5-F10
A12: Biên EBITDA % | B12: =IF(B3=0,0,B11/B3) | C12: =IF(C3=0,0,C11/C3) | D12: =IF(D3=0,0,D11/D3) | E12: =IF(E3=0,0,E11/E3) | F12: =IF(F3=0,0,F11/F3)
A13: Khấu hao | B13: 0.02 | C13: 0.05 | D13: 0.15 | E13: 0.4 | F13: 0.9
A14: EBIT | B14: =B11-B13 | C14: =C11-C13 | D14: =D11-D13 | E14: =E11-E13 | F14: =F11-F13
A15: Chi phí lãi vay | B15: 0 | C15: 0 | D15: 0 | E15: 0 | F15: 0
A16: Thuế | B16: =MAX(0,B14-B15)*'Giả định'!B41 | C16: =MAX(0,C14-C15)*'Giả định'!C41 | D16: =MAX(0,D14-D15)*'Giả định'!D41 | E16: =MAX(0,E14-E15)*'Giả định'!E41 | F16: =MAX(0,F14-F15)*'Giả định'!F41
A17: Lãi ròng | B17: =B14-B15-B16 | C17: =C14-C15-C16 | D17: =D14-D15-D16 | E17: =E14-E15-E16 | F17: =F14-F15-F16
A18: Biên ròng % | B18: =IF(B3=0,0,B17/B3) | C18: =IF(C3=0,0,C17/C3) | D18: =IF(D3=0,0,D17/D3) | E18: =IF(E3=0,0,E17/E3) | F18: =IF(F3=0,0,F17/F3)

Sheet Dòng tiền
A1: Báo cáo Dòng tiền
A2: Item | B2: 2026 | C2: 2027 | D2: 2028 | E2: 2029 | F2: 2030
A3: Lãi ròng | B3: ='Lãi-Lỗ'!B17 | C3: ='Lãi-Lỗ'!C17 | D3: ='Lãi-Lỗ'!D17 | E3: ='Lãi-Lỗ'!E17 | F3: ='Lãi-Lỗ'!F17
A4: + Khấu hao | B4: ='Lãi-Lỗ'!B13 | C4: ='Lãi-Lỗ'!C13 | D4: ='Lãi-Lỗ'!D13 | E4: ='Lãi-Lỗ'!E13 | F4: ='Lãi-Lỗ'!F13
A5: + Thay đổi vốn lưu động | B5: -0.04 | C5: =-('Mô hình Doanh thu'!D12-'Mô hình Doanh thu'!C12)*0.05 | D5: =-('Mô hình Doanh thu'!E12-'Mô hình Doanh thu'!D12)*0.05 | E5: =-('Mô hình Doanh thu'!F12-'Mô hình Doanh thu'!E12)*0.05 | F5: =-('Mô hình Doanh thu'!G12-'Mô hình Doanh thu'!F12)*0.05
A6: Dòng tiền hoạt động | B6: =B3+B4+B5 | C6: =C3+C4+C5 | D6: =D3+D4+D5 | E6: =E3+E4+E5 | F6: =F3+F4+F5
A7: CapEx | B7: -0.1 | C7: -0.3 | D7: -0.8 | E7: -2 | F7: -4.5
A8: Dòng tiền đầu tư | B8: =B7 | C8: =C7 | D8: =D7 | E8: =E7 | F8: =F7
A9: Huy động vốn cổ phần | B9: 3 | C9: 0 | D9: 12 | E9: 0 | F9: 0
A10: Dòng tiền tài chính | B10: =B9 | C10: =C9 | D10: =D9 | E10: =E9 | F10: =F9
A11: Thay đổi tiền ròng | B11: =B6+B8+B10 | C11: =C6+C8+C10 | D11: =D6+D8+D10 | E11: =E6+E8+E10 | F11: =F6+F8+F10
A12: Tiền đầu kỳ | B12: 0.2 | C12: =B13 | D12: =C13 | E12: =D13 | F12: =E13
A13: Tiền cuối kỳ | B13: =B12+B11 | C13: =C12+C11 | D13: =D12+D11 | E13: =E12+E11 | F13: =F12+F11

Sheet KPI Tóm tắt
A1: KPI Tóm tắt
A2: Metric | B2: 2026 | C2: 2027 | D2: 2028 | E2: 2029 | F2: 2030
A3: Thành viên trả phí (cuối năm) | B3: ='Giả định'!B5 | C3: ='Giả định'!C5 | D3: ='Giả định'!D5 | E3: ='Giả định'!E5 | F3: ='Giả định'!F5
A4: Thành viên miễn phí (cuối năm) | B4: ='Giả định'!B6 | C4: ='Giả định'!C6 | D4: ='Giả định'!D6 | E4: ='Giả định'!E6 | F4: ='Giả định'!F6
A5: Tổng thành viên | B5: ='Giả định'!B5+'Giả định'!B6 | C5: ='Giả định'!C5+'Giả định'!C6 | D5: ='Giả định'!D5+'Giả định'!D6 | E5: ='Giả định'!E5+'Giả định'!E6 | F5: ='Giả định'!F5+'Giả định'!F6
A6: ARPU trả phí (USD) | B6: =IF('Giả định'!B5=0,0,'Mô hình Doanh thu'!C12*1000000/'Giả định'!B5) | C6: =IF('Giả định'!C5=0,0,'Mô hình Doanh thu'!D12*1000000/'Giả định'!C5) | D6: =IF('Giả định'!D5=0,0,'Mô hình Doanh thu'!E12*1000000/'Giả định'!D5) | E6: =IF('Giả định'!E5=0,0,'Mô hình Doanh thu'!F12*1000000/'Giả định'!E5) | F6: =IF('Giả định'!F5=0,0,'Mô hình Doanh thu'!G12*1000000/'Giả định'!F5)
A7: Tỷ lệ free→paid | B7: ='Giả định'!B9 | C7: ='Giả định'!C9 | D7: ='Giả định'!D9 | E7: ='Giả định'!E9 | F7: ='Giả định'!F9
A8: Churn năm | B8: ='Giả định'!B8 | C8: ='Giả định'!C8 | D8: ='Giả định'!D8 | E8: ='Giả định'!E8 | F8: ='Giả định'!F8
A9: CAC (USD) | B9: 38 | C9: 32 | D9: 28 | E9: 25 | F9: 23
A10: LTV (USD) | B10: 185 | C10: 245 | D10: 320 | E10: 420 | F10: 510
A11: Tỷ lệ LTV/CAC | B11: =B10/B9 | C11: =C10/C9 | D11: =D10/D9 | E11: =E10/E9 | F11: =F10/F9
A12: Doanh thu (Triệu USD) | B12: ='Mô hình Doanh thu'!C12 | C12: ='Mô hình Doanh thu'!D12 | D12: ='Mô hình Doanh thu'!E12 | E12: ='Mô hình Doanh thu'!F12 | F12: ='Mô hình Doanh thu'!G12
A13: Biên gộp % | B13: ='Lãi-Lỗ'!B6 | C13: ='Lãi-Lỗ'!C6 | D13: ='Lãi-Lỗ'!D6 | E13: ='Lãi-Lỗ'!E6 | F13: ='Lãi-Lỗ'!F6
A14: Biên EBITDA % | B14: ='Lãi-Lỗ'!B12 | C14: ='Lãi-Lỗ'!C12 | D14: ='Lãi-Lỗ'!D12 | E14: ='Lãi-Lỗ'!E12 | F14: ='Lãi-Lỗ'!F12
A15: Runway tiền mặt (tháng) | B15: 24 | C15: 30 | D15: 36 | E15: 42 | F15: 48
A16: Nhân sự | B16: 8 | C16: 22 | D16: 48 | E16: 95 | F16: 160

Sheet Định giá
A1: Phân tích Định giá
A2: Item | B2: 2026 | C2: 2027 | D2: 2028 | E2: 2029 | F2: 2030
A3: Doanh thu (Triệu USD) | B3: ='Mô hình Doanh thu'!C12 | C3: ='Mô hình Doanh thu'!D12 | D3: ='Mô hình Doanh thu'!E12 | E3: ='Mô hình Doanh thu'!F12 | F3: ='Mô hình Doanh thu'!G12
A4: Hệ số doanh thu | B4: ='Giả định'!B43 | C4: ='Giả định'!C43 | D4: ='Giả định'!D43 | E4: ='Giả định'!E43 | F4: ='Giả định'!F43
A5: Định giá Thấp (Triệu USD) | B5: =B3*B4*0.78 | C5: =C3*C4*0.78 | D5: =D3*D4*0.78 | E5: =E3*E4*0.78 | F5: =F3*F4*0.78
A6: Định giá Trung (Triệu USD) | B6: =B3*B4 | C6: =C3*C4 | D6: =D3*D4 | E6: =E3*E4 | F6: =F3*F4
A7: Định giá Cao (Triệu USD) | B7: =B3*B4*1.20 | C7: =C3*C4*1.20 | D7: =D3*D4*1.20 | E7: =E3*E4*1.20 | F7: =F3*F4*1.20
A8: EBITDA (Triệu USD) | B8: ='Lãi-Lỗ'!B11 | C8: ='Lãi-Lỗ'!C11 | D8: ='Lãi-Lỗ'!D11 | E8: ='Lãi-Lỗ'!E11 | F8: ='Lãi-Lỗ'!F11
A9: Hệ số EBITDA | B9: ='Giả định'!B44 | C9: ='Giả định'!C44 | D9: ='Giả định'!D44 | E9: ='Giả định'!E44 | F9: ='Giả định'!F44
A10: Định giá theo EBITDA (Triệu USD) | B10: =IF(B8<=0,0,B8*B9) | C10: =IF(C8<=0,0,C8*C9) | D10: =IF(D8<=0,0,D8*D9) | E10: =IF(E8<=0,0,E8*E9) | F10: =IF(F8<=0,0,F8*F9)
A11: DCF giá trị cuối kỳ (Triệu USD) | B11: "-" | C11: "-" | D11: "-" | E11: "-" | F11: ='Lãi-Lỗ'!F17*1.04/('Giả định'!B42-0.04)

Sheet Kịch bản
A1: Phân tích Nhạy cảm / Kịch bản
A2: Kịch bản | B2: Bi quan | C2: Cơ bản | D2: Lạc quan
A3: Y3 Revenue (USD M) | B3: 6 | C3: 14.5 | D3: 22
A4: Y5 Revenue (USD M) | B4: 35 | C4: 98 | D4: 165
A5: Y5 EBITDA margin | B5: 0.1 | C5: 0.22 | D5: 0.32
A6: Y5 Valuation mid (USD M) | B6: 175 | C6: 615 | D6: 1150
A7: Investor share @ 21.4% pre-dilution | B7: 37.5 | C7: 131.6 | D7: 246.1
A8: MOIC (pre-dilution) | B8: 12.5 | C8: 43.9 | D8: 82
A9: MOIC (post 30% dilution) | B9: 8.75 | C9: 30.73 | D9: 57.4
A10: IRR (5Y) | B10: 0.54 | C10: 1.16 | D10: 1.55
A13: Ghi chú
A14: Bi quan | B14: Áp dụng chậm, chỉ VN, không mở rộng SEA
A15: Cơ bản | B15: Thực thi đúng kế hoạch roadmap
A16: Lạc quan | B16: SEA + B2B tăng tốc, vào tiếng Anh sớm
