Workbook

Sheet Cover
B2: VETUONGLAI ECOSYSTEM
B3: 5-Year Financial Projections
B5: Period: 2026 (Year 1) — 2030 (Year 5)
B6: Currency: USD millions unless otherwise noted
B7: May 2026
B9: STRICTLY CONFIDENTIAL — Authorized recipients only
B11: Color legend
B12: Blue text | C12: Hardcoded inputs (change for scenarios)
B13: Black text | C13: All formulas and calculations
B14: Green text | C14: Cross-sheet links
B15: Yellow background | C15: Key assumptions needing attention
B18: Sheets in this workbook
B19: → Assumptions
B20: → Revenue Model
B21: → Cost & Opex
B22: → P&L
B23: → Cash Flow
B24: → KPI Summary
B25: → Valuation
B26: → Scenarios

Sheet Assumptions
A1: Vetuonglai 5-Year Financial Projections
A2: Year | B2: 2026 | C2: 2027 | D2: 2028 | E2: 2029 | F2: 2030
A4: MEMBER GROWTH
A5: Paid members (end of year) | B5: 12000 | C5: 55000 | D5: 220000 | E5: 620000 | F5: 1650000
A6: Free members (end of year) | B6: 108000 | C6: 495000 | D6: 1980000 | E6: 5580000 | F6: 14850000
A7: Total members | B7: =B5+B6 | C7: =C5+C6 | D7: =D5+D6 | E7: =E5+E6 | F7: =F5+F6
A8: YoY paid member growth | B8: "-" | C8: =C5/B5-1 | D8: =D5/C5-1 | E8: =E5/D5-1 | F8: =F5/E5-1
A9: Annual churn | B9: 0.18 | C9: 0.15 | D9: 0.12 | E9: 0.1 | F9: 0.09
A10: Free→paid conversion | B10: 0.05 | C10: 0.07 | D10: 0.09 | E10: 0.11 | F10: 0.12
A12: PRICING (USD)
A13: Annual Access price | B13: 99 | C13: 104 | D13: 109 | E13: 115 | F13: 121
A14: Specialist Pack price (avg) | B14: 29 | C14: 31 | D14: 32 | E14: 34 | F14: 36
A15: AI Tutor price/year | B15: 120 | C15: 126 | D15: 132 | E15: 139 | F15: 146
A16: B2B Verification API ($/verif) | B16: 0.75 | C16: 0.8 | D16: 0.85 | E16: 0.9 | F16: 0.95
A17: B2B VC Issuer License/year | B17: 12000 | C17: 12500 | D17: 13000 | E17: 13500 | F17: 14000
A19: TAKE RATES & VOLUME
A20: Pack attach rate per paid member/yr | B20: 1.2 | C20: 1.5 | D20: 1.8 | E20: 2 | F20: 2.2
A21: AI Tutor attach % paid | B21: 0.1 | C21: 0.18 | D21: 0.25 | E21: 0.32 | F21: 0.38
A22: Job marketplace GMV ($M) | B22: 2 | C22: 12 | D22: 48 | E22: 145 | F22: 360
A23: Marketplace take rate % | B23: 0.09 | C23: 0.09 | D23: 0.085 | E23: 0.08 | F23: 0.08
A24: Wallet payout volume ($M) | B24: 1 | C24: 8 | D24: 35 | E24: 105 | F24: 250
A25: Wallet payout fee % | B25: 0.02 | C25: 0.02 | D25: 0.018 | E25: 0.015 | F25: 0.012
A26: Affiliate revenue ($M) | B26: 0.05 | C26: 0.4 | D26: 1.8 | E26: 5.5 | F26: 13.5
A27: B2B API verifications (M/year) | B27: 0.5 | C27: 3 | D27: 12 | E27: 35 | F27: 80
A28: B2B VC Issuer customers | B28: 2 | C28: 12 | D28: 45 | E28: 130 | F28: 320
A30: COST RATIOS
A31: Infrastructure cost % of revenue | B31: 0.06 | C31: 0.05 | D31: 0.04 | E31: 0.035 | F31: 0.03
A32: Payment processing % of revenue | B32: 0.025 | C32: 0.025 | D32: 0.024 | E32: 0.023 | F32: 0.022
A33: KYC + verification cost % rev | B33: 0.02 | C33: 0.018 | D33: 0.015 | E33: 0.012 | F33: 0.01
A34: Other COGS % of revenue | B34: 0.175 | C34: 0.147 | D34: 0.141 | E34: 0.13 | F34: 0.128
A35: Total COGS % (sum above) | B35: =B31+B32+B33+B34 | C35: =C31+C32+C33+C34 | D35: =D31+D32+D33+D34 | E35: =E31+E32+E33+E34 | F35: =F31+F32+F33+F34
A36: S&M cost % of revenue | B36: 0.45 | C36: 0.38 | D36: 0.32 | E36: 0.28 | F36: 0.25
A37: R&D cost % of revenue | B37: 0.35 | C37: 0.28 | D37: 0.22 | E37: 0.18 | F37: 0.15
A38: G&A cost % of revenue | B38: 0.18 | C38: 0.14 | D38: 0.1 | E38: 0.08 | F38: 0.07
A40: MACRO & VALUATION
A41: Effective tax rate | B41: 0 | C41: 0 | D41: 0.1 | E41: 0.2 | F41: 0.2
A42: Discount rate (WACC) | B42: 0.18
A43: Revenue multiple (mid) | B43: 10 | C43: 9.5 | D43: 7.5 | E43: 6.3 | F43: 6.3
A44: EBITDA multiple | B44: 0 | C44: 0 | D44: 25 | E44: 18 | F44: 15

Sheet Revenue Model
A1: Revenue Model (USD M)
A2: Lane | B2: Description | C2: 2026 | D2: 2027 | E2: 2028 | F2: 2029 | G2: 2030
A3: Annual Access subscription | B3: B2C subscription — Lifetime Unlock | C3: ='Assumptions'!B5*'Assumptions'!B13/1000000*0.5 | D3: ='Assumptions'!C5*'Assumptions'!C13/1000000*1.0 | E3: ='Assumptions'!D5*'Assumptions'!D13/1000000*1.0 | F3: ='Assumptions'!E5*'Assumptions'!E13/1000000*1.0 | G3: ='Assumptions'!F5*'Assumptions'!F13/1000000*1.0
A4: Specialist Packs | B4: B2C one-off purchases | C4: ='Assumptions'!B5*'Assumptions'!B20*'Assumptions'!B14/1000000 | D4: ='Assumptions'!C5*'Assumptions'!C20*'Assumptions'!C14/1000000 | E4: ='Assumptions'!D5*'Assumptions'!D20*'Assumptions'!D14/1000000 | F4: ='Assumptions'!E5*'Assumptions'!E20*'Assumptions'!E14/1000000 | G4: ='Assumptions'!F5*'Assumptions'!F20*'Assumptions'!F14/1000000
A5: Job Marketplace take-rate | B5: Escrow + payout fees | C5: ='Assumptions'!B22*'Assumptions'!B23 | D5: ='Assumptions'!C22*'Assumptions'!C23 | E5: ='Assumptions'!D22*'Assumptions'!D23 | F5: ='Assumptions'!E22*'Assumptions'!E23 | G5: ='Assumptions'!F22*'Assumptions'!F23
A6: Wallet payout fees | B6: Free-tier 2% on withdrawals | C6: ='Assumptions'!B24*'Assumptions'!B25 | D6: ='Assumptions'!C24*'Assumptions'!C25 | E6: ='Assumptions'!D24*'Assumptions'!D25 | F6: ='Assumptions'!E24*'Assumptions'!E25 | G6: ='Assumptions'!F24*'Assumptions'!F25
A7: Affiliate revenue share | B7: Pass-through commissions | C7: ='Assumptions'!B26 | D7: ='Assumptions'!C26 | E7: ='Assumptions'!D26 | F7: ='Assumptions'!E26 | G7: ='Assumptions'!F26
A8: B2B Identity Verification API | B8: Per-verification charges | C8: ='Assumptions'!B27*'Assumptions'!B16 | D8: ='Assumptions'!C27*'Assumptions'!C16 | E8: ='Assumptions'!D27*'Assumptions'!D16 | F8: ='Assumptions'!E27*'Assumptions'!E16 | G8: ='Assumptions'!F27*'Assumptions'!F16
A9: B2B VC Issuer Licensing | B9: Annual licenses for credential issuers | C9: ='Assumptions'!B28*'Assumptions'!B17/1000000 | D9: ='Assumptions'!C28*'Assumptions'!C17/1000000 | E9: ='Assumptions'!D28*'Assumptions'!D17/1000000 | F9: ='Assumptions'!E28*'Assumptions'!E17/1000000 | G9: ='Assumptions'!F28*'Assumptions'!F17/1000000
A10: AI Tutor Premium | B10: Anthropic-powered tutoring | C10: ='Assumptions'!B5*'Assumptions'!B21*'Assumptions'!B15/1000000 | D10: ='Assumptions'!C5*'Assumptions'!C21*'Assumptions'!C15/1000000 | E10: ='Assumptions'!D5*'Assumptions'!D21*'Assumptions'!D15/1000000 | F10: ='Assumptions'!E5*'Assumptions'!E21*'Assumptions'!E15/1000000 | G10: ='Assumptions'!F5*'Assumptions'!F21*'Assumptions'!F15/1000000
A12: Total revenue | C12: =SUM(C3:C10) | D12: =SUM(D3:D10) | E12: =SUM(E3:E10) | F12: =SUM(F3:F10) | G12: =SUM(G3:G10)

Sheet Cost & Opex
A1: Cost & Operating Expense Breakdown
A2: Item | B2: 2026 | C2: 2027 | D2: 2028 | E2: 2029 | F2: 2030
A3: Infrastructure (Cloudflare, KV, monitoring) | B3: ='Revenue Model'!C12*'Assumptions'!B35*('Assumptions'!B31/'Assumptions'!B35) | C3: ='Revenue Model'!D12*'Assumptions'!C35*('Assumptions'!C31/'Assumptions'!C35) | D3: ='Revenue Model'!E12*'Assumptions'!D35*('Assumptions'!D31/'Assumptions'!D35) | E3: ='Revenue Model'!F12*'Assumptions'!E35*('Assumptions'!E31/'Assumptions'!E35) | F3: ='Revenue Model'!G12*'Assumptions'!F35*('Assumptions'!F31/'Assumptions'!F35)
A4: Payment processing (Stripe/PayPal) | B4: ='Revenue Model'!C12*'Assumptions'!B32 | C4: ='Revenue Model'!D12*'Assumptions'!C32 | D4: ='Revenue Model'!E12*'Assumptions'!D32 | E4: ='Revenue Model'!F12*'Assumptions'!E32 | F4: ='Revenue Model'!G12*'Assumptions'!F32
A5: KYC + identity verification | B5: ='Revenue Model'!C12*'Assumptions'!B33 | C5: ='Revenue Model'!D12*'Assumptions'!C33 | D5: ='Revenue Model'!E12*'Assumptions'!D33 | E5: ='Revenue Model'!F12*'Assumptions'!E33 | F5: ='Revenue Model'!G12*'Assumptions'!F33
A6: Other COGS (support, content, misc) | B6: ='Revenue Model'!C12*'Assumptions'!B34 | C6: ='Revenue Model'!D12*'Assumptions'!C34 | D6: ='Revenue Model'!E12*'Assumptions'!D34 | E6: ='Revenue Model'!F12*'Assumptions'!E34 | F6: ='Revenue Model'!G12*'Assumptions'!F34
A7: Total COGS | B7: ='Revenue Model'!C12*'Assumptions'!B35 | C7: ='Revenue Model'!D12*'Assumptions'!C35 | D7: ='Revenue Model'!E12*'Assumptions'!D35 | E7: ='Revenue Model'!F12*'Assumptions'!E35 | F7: ='Revenue Model'!G12*'Assumptions'!F35
A8: Sales & Marketing | B8: ='Revenue Model'!C12*'Assumptions'!B36 | C8: ='Revenue Model'!D12*'Assumptions'!C36 | D8: ='Revenue Model'!E12*'Assumptions'!D36 | E8: ='Revenue Model'!F12*'Assumptions'!E36 | F8: ='Revenue Model'!G12*'Assumptions'!F36
A9: R&D / Engineering | B9: ='Revenue Model'!C12*'Assumptions'!B37 | C9: ='Revenue Model'!D12*'Assumptions'!C37 | D9: ='Revenue Model'!E12*'Assumptions'!D37 | E9: ='Revenue Model'!F12*'Assumptions'!E37 | F9: ='Revenue Model'!G12*'Assumptions'!F37
A10: G&A | B10: ='Revenue Model'!C12*'Assumptions'!B38 | C10: ='Revenue Model'!D12*'Assumptions'!C38 | D10: ='Revenue Model'!E12*'Assumptions'!D38 | E10: ='Revenue Model'!F12*'Assumptions'!E38 | F10: ='Revenue Model'!G12*'Assumptions'!F38
A11: Total Operating Expenses | B11: ='Revenue Model'!C12*('Assumptions'!B36+'Assumptions'!B37+'Assumptions'!B38) | C11: ='Revenue Model'!D12*('Assumptions'!C36+'Assumptions'!C37+'Assumptions'!C38) | D11: ='Revenue Model'!E12*('Assumptions'!D36+'Assumptions'!D37+'Assumptions'!D38) | E11: ='Revenue Model'!F12*('Assumptions'!E36+'Assumptions'!E37+'Assumptions'!E38) | F11: ='Revenue Model'!G12*('Assumptions'!F36+'Assumptions'!F37+'Assumptions'!F38)

Sheet P&L
A1: P&L
A2: Item | B2: 2026 | C2: 2027 | D2: 2028 | E2: 2029 | F2: 2030
A3: Revenue | B3: ='Revenue Model'!C12 | C3: ='Revenue Model'!D12 | D3: ='Revenue Model'!E12 | E3: ='Revenue Model'!F12 | F3: ='Revenue Model'!G12
A4: COGS (infra + payments + KYC) | B4: =B3*'Assumptions'!B35 | C4: =C3*'Assumptions'!C35 | D4: =D3*'Assumptions'!D35 | E4: =E3*'Assumptions'!E35 | F4: =F3*'Assumptions'!F35
A5: Gross profit | B5: =B3-B4 | C5: =C3-C4 | D5: =D3-D4 | E5: =E3-E4 | F5: =F3-F4
A6: Gross margin % | B6: =IF(B3=0,0,B5/B3) | C6: =IF(C3=0,0,C5/C3) | D6: =IF(D3=0,0,D5/D3) | E6: =IF(E3=0,0,E5/E3) | F6: =IF(F3=0,0,F5/F3)
A7: Sales & Marketing | B7: =B3*'Assumptions'!B36 | C7: =C3*'Assumptions'!C36 | D7: =D3*'Assumptions'!D36 | E7: =E3*'Assumptions'!E36 | F7: =F3*'Assumptions'!F36
A8: R&D / Engineering | B8: =B3*'Assumptions'!B37 | C8: =C3*'Assumptions'!C37 | D8: =D3*'Assumptions'!D37 | E8: =E3*'Assumptions'!E37 | F8: =F3*'Assumptions'!F37
A9: G&A | B9: =B3*'Assumptions'!B38 | C9: =C3*'Assumptions'!C38 | D9: =D3*'Assumptions'!D38 | E9: =E3*'Assumptions'!E38 | F9: =F3*'Assumptions'!F38
A10: Total Opex | B10: =B7+B8+B9 | C10: =C7+C8+C9 | D10: =D7+D8+D9 | E10: =E7+E8+E9 | F10: =F7+F8+F9
A11: EBITDA | B11: =B5-B10 | C11: =C5-C10 | D11: =D5-D10 | E11: =E5-E10 | F11: =F5-F10
A12: EBITDA margin % | B12: =IF(B3=0,0,B11/B3) | C12: =IF(C3=0,0,C11/C3) | D12: =IF(D3=0,0,D11/D3) | E12: =IF(E3=0,0,E11/E3) | F12: =IF(F3=0,0,F11/F3)
A13: Depreciation & Amortization | B13: 0.02 | C13: 0.05 | D13: 0.15 | E13: 0.4 | F13: 0.9
A14: EBIT | B14: =B11-B13 | C14: =C11-C13 | D14: =D11-D13 | E14: =E11-E13 | F14: =F11-F13
A15: Interest expense | B15: 0 | C15: 0 | D15: 0 | E15: 0 | F15: 0
A16: Tax | B16: =MAX(0,B14-B15)*'Assumptions'!B41 | C16: =MAX(0,C14-C15)*'Assumptions'!C41 | D16: =MAX(0,D14-D15)*'Assumptions'!D41 | E16: =MAX(0,E14-E15)*'Assumptions'!E41 | F16: =MAX(0,F14-F15)*'Assumptions'!F41
A17: Net Income | B17: =B14-B15-B16 | C17: =C14-C15-C16 | D17: =D14-D15-D16 | E17: =E14-E15-E16 | F17: =F14-F15-F16
A18: Net margin % | B18: =IF(B3=0,0,B17/B3) | C18: =IF(C3=0,0,C17/C3) | D18: =IF(D3=0,0,D17/D3) | E18: =IF(E3=0,0,E17/E3) | F18: =IF(F3=0,0,F17/F3)

Sheet Cash Flow
A1: Cash Flow Statement
A2: Item | B2: 2026 | C2: 2027 | D2: 2028 | E2: 2029 | F2: 2030
A3: Net Income | B3: ='P&L'!B17 | C3: ='P&L'!C17 | D3: ='P&L'!D17 | E3: ='P&L'!E17 | F3: ='P&L'!F17
A4: + D&A | B4: ='P&L'!B13 | C4: ='P&L'!C13 | D4: ='P&L'!D13 | E4: ='P&L'!E13 | F4: ='P&L'!F13
A5: + Changes in working capital | B5: -0.04 | C5: =-('Revenue Model'!D12-'Revenue Model'!C12)*0.05 | D5: =-('Revenue Model'!E12-'Revenue Model'!D12)*0.05 | E5: =-('Revenue Model'!F12-'Revenue Model'!E12)*0.05 | F5: =-('Revenue Model'!G12-'Revenue Model'!F12)*0.05
A6: Cash from operations | B6: =B3+B4+B5 | C6: =C3+C4+C5 | D6: =D3+D4+D5 | E6: =E3+E4+E5 | F6: =F3+F4+F5
A7: CapEx | B7: -0.1 | C7: -0.3 | D7: -0.8 | E7: -2 | F7: -4.5
A8: Cash from investing | B8: =B7 | C8: =C7 | D8: =D7 | E8: =E7 | F8: =F7
A9: Equity raises | B9: 3 | C9: 0 | D9: 12 | E9: 0 | F9: 0
A10: Cash from financing | B10: =B9 | C10: =C9 | D10: =D9 | E10: =E9 | F10: =F9
A11: Net change in cash | B11: =B6+B8+B10 | C11: =C6+C8+C10 | D11: =D6+D8+D10 | E11: =E6+E8+E10 | F11: =F6+F8+F10
A12: Beginning cash | B12: 0.2 | C12: =B13 | D12: =C13 | E12: =D13 | F12: =E13
A13: Ending cash | B13: =B12+B11 | C13: =C12+C11 | D13: =D12+D11 | E13: =E12+E11 | F13: =F12+F11

Sheet KPI Summary
A1: KPI Summary
A2: Metric | B2: 2026 | C2: 2027 | D2: 2028 | E2: 2029 | F2: 2030
A3: Paid members (end of year) | B3: ='Assumptions'!B5 | C3: ='Assumptions'!C5 | D3: ='Assumptions'!D5 | E3: ='Assumptions'!E5 | F3: ='Assumptions'!F5
A4: Free members (end of year) | B4: ='Assumptions'!B6 | C4: ='Assumptions'!C6 | D4: ='Assumptions'!D6 | E4: ='Assumptions'!E6 | F4: ='Assumptions'!F6
A5: Total members | B5: ='Assumptions'!B5+'Assumptions'!B6 | C5: ='Assumptions'!C5+'Assumptions'!C6 | D5: ='Assumptions'!D5+'Assumptions'!D6 | E5: ='Assumptions'!E5+'Assumptions'!E6 | F5: ='Assumptions'!F5+'Assumptions'!F6
A6: ARPU paid (USD) | B6: =IF('Assumptions'!B5=0,0,'Revenue Model'!C12*1000000/'Assumptions'!B5) | C6: =IF('Assumptions'!C5=0,0,'Revenue Model'!D12*1000000/'Assumptions'!C5) | D6: =IF('Assumptions'!D5=0,0,'Revenue Model'!E12*1000000/'Assumptions'!D5) | E6: =IF('Assumptions'!E5=0,0,'Revenue Model'!F12*1000000/'Assumptions'!E5) | F6: =IF('Assumptions'!F5=0,0,'Revenue Model'!G12*1000000/'Assumptions'!F5)
A7: Free→paid conversion | B7: ='Assumptions'!B9 | C7: ='Assumptions'!C9 | D7: ='Assumptions'!D9 | E7: ='Assumptions'!E9 | F7: ='Assumptions'!F9
A8: Annual churn | B8: ='Assumptions'!B8 | C8: ='Assumptions'!C8 | D8: ='Assumptions'!D8 | E8: ='Assumptions'!E8 | F8: ='Assumptions'!F8
A9: CAC (USD) | B9: 38 | C9: 32 | D9: 28 | E9: 25 | F9: 23
A10: LTV (USD) | B10: 185 | C10: 245 | D10: 320 | E10: 420 | F10: 510
A11: LTV/CAC ratio | B11: =B10/B9 | C11: =C10/C9 | D11: =D10/D9 | E11: =E10/E9 | F11: =F10/F9
A12: Revenue (USD M) | B12: ='Revenue Model'!C12 | C12: ='Revenue Model'!D12 | D12: ='Revenue Model'!E12 | E12: ='Revenue Model'!F12 | F12: ='Revenue Model'!G12
A13: Gross margin % | B13: ='P&L'!B6 | C13: ='P&L'!C6 | D13: ='P&L'!D6 | E13: ='P&L'!E6 | F13: ='P&L'!F6
A14: EBITDA margin % | B14: ='P&L'!B12 | C14: ='P&L'!C12 | D14: ='P&L'!D12 | E14: ='P&L'!E12 | F14: ='P&L'!F12
A15: Cash runway months | B15: 24 | C15: 30 | D15: 36 | E15: 42 | F15: 48
A16: Headcount | B16: 8 | C16: 22 | D16: 48 | E16: 95 | F16: 160

Sheet Valuation
A1: Valuation Analysis
A2: Item | B2: 2026 | C2: 2027 | D2: 2028 | E2: 2029 | F2: 2030
A3: Revenue (USD M) | B3: ='Revenue Model'!C12 | C3: ='Revenue Model'!D12 | D3: ='Revenue Model'!E12 | E3: ='Revenue Model'!F12 | F3: ='Revenue Model'!G12
A4: Revenue multiple | B4: ='Assumptions'!B43 | C4: ='Assumptions'!C43 | D4: ='Assumptions'!D43 | E4: ='Assumptions'!E43 | F4: ='Assumptions'!F43
A5: Valuation Low (USD M) | B5: =B3*B4*0.78 | C5: =C3*C4*0.78 | D5: =D3*D4*0.78 | E5: =E3*E4*0.78 | F5: =F3*F4*0.78
A6: Valuation Mid (USD M) | B6: =B3*B4 | C6: =C3*C4 | D6: =D3*D4 | E6: =E3*E4 | F6: =F3*F4
A7: Valuation High (USD M) | B7: =B3*B4*1.20 | C7: =C3*C4*1.20 | D7: =D3*D4*1.20 | E7: =E3*E4*1.20 | F7: =F3*F4*1.20
A8: EBITDA (USD M) | B8: ='P&L'!B11 | C8: ='P&L'!C11 | D8: ='P&L'!D11 | E8: ='P&L'!E11 | F8: ='P&L'!F11
A9: EBITDA multiple | B9: ='Assumptions'!B44 | C9: ='Assumptions'!C44 | D9: ='Assumptions'!D44 | E9: ='Assumptions'!E44 | F9: ='Assumptions'!F44
A10: EBITDA-based valuation (USD M) | B10: =IF(B8<=0,0,B8*B9) | C10: =IF(C8<=0,0,C8*C9) | D10: =IF(D8<=0,0,D8*D9) | E10: =IF(E8<=0,0,E8*E9) | F10: =IF(F8<=0,0,F8*F9)
A11: DCF terminal value (USD M) | B11: "-" | C11: "-" | D11: "-" | E11: "-" | F11: ='P&L'!F17*1.04/('Assumptions'!B42-0.04)

Sheet Scenarios
A1: Sensitivity / Scenario Analysis
A2: Scenario | B2: Bear | C2: Base | D2: Bull
A3: Y3 Revenue (USD M) | B3: 6 | C3: 14.5 | D3: 22
A4: Y5 Revenue (USD M) | B4: 35 | C4: 98 | D4: 165
A5: Y5 EBITDA margin | B5: 0.1 | C5: 0.22 | D5: 0.32
A6: Y5 Valuation mid (USD M) | B6: 175 | C6: 615 | D6: 1150
A7: Investor share @ 21.4% pre-dilution | B7: 37.5 | C7: 131.6 | D7: 246.1
A8: MOIC (pre-dilution) | B8: 12.5 | C8: 43.9 | D8: 82
A9: MOIC (post 30% dilution) | B9: 8.75 | C9: 30.73 | D9: 57.4
A10: IRR (5Y) | B10: 0.54 | C10: 1.16 | D10: 1.55
A13: Notes
A14: Bear | B14: Slow adoption, Vietnam-only, no SEA expansion
A15: Base | B15: Planned execution per roadmap
A16: Bull | B16: SEA + B2B accelerate, English market early entry
